cexi/__init__.py
cexi/__main__.py
cexi/binary.py
cexi/constants.py
cexi/core.py
cexi/exceptions.py
cexi/extension.py
cexi/misc.py
cexi/proxy.py
cexi/statement.py
cexi/templates.py
cexi/typing.py
cexi-0.0.3.dist-info/LICENSE
cexi-0.0.3.dist-info/METADATA
cexi-0.0.3.dist-info/WHEEL
cexi-0.0.3.dist-info/top_level.txt
cexi-0.0.3.dist-info/RECORD
