Metadata-Version: 2.1
Name: cexi
Version: 0.0.3
Summary: Cee EXtensions Interpolation
Home-page: https://github.com/one-two-four-cee-four-one-plus/cexi
Author: melvin kaye
Author-email: one.two.four.cee.four.one.plus@gmail.com
Classifier: Programming Language :: Python :: 3
Classifier: License :: OSI Approved :: BSD License
Classifier: Operating System :: POSIX :: Linux
Requires-Python: >=3.9
License-File: LICENSE
